flask_bpjs.py
Flask_Bpjs-0.0.5.dist-info/LICENSE
Flask_Bpjs-0.0.5.dist-info/METADATA
Flask_Bpjs-0.0.5.dist-info/WHEEL
Flask_Bpjs-0.0.5.dist-info/top_level.txt
Flask_Bpjs-0.0.5.dist-info/RECORD
