Metadata-Version: 2.1
Name: Flask-Bpjs
Version: 0.0.5
Summary: Bpjs on flask
Home-page: https://github.com/GatLab/Flask-Bpjs.git
Author: Gatlab
Author-email: Gatlab <dev@gatlab.co>
License: Copyright 2022 Gatlab <dev@gatlab.co>        
Project-URL: Homepage, https://github.com/GatLab/Flask-Bpjs
Project-URL: Bug Tracker, https://github.com/GatLab/Flask-Bpjs/issues
Keywords: flask,bpjs
Platform: any
Classifier: Programming Language :: Python :: 3
Classifier: License :: OSI Approved :: MIT License
Classifier: Operating System :: OS Independent
Requires-Python: >=3.8
License-File: LICENSE
Requires-Dist: Flask
Requires-Dist: lzstring
Requires-Dist: pycryptodome
